pymoodle_jku/__init__.py
pymoodle_jku/pymoodle.py
pymoodle_jku/classes/course.py
pymoodle_jku/classes/course_data.py
pymoodle_jku/classes/evaluation.py
pymoodle_jku/classes/events.py
pymoodle_jku/classes/exceptions.py
pymoodle_jku/client/client.py
pymoodle_jku/client/download_manager.py
pymoodle_jku/client/html_parser.py
pymoodle_jku/scripts/basic.py
pymoodle_jku/scripts/downloading.py
pymoodle_jku/scripts/grades.py
pymoodle_jku/scripts/timetable.py
pymoodle_jku/utils/config.py
pymoodle_jku/utils/config_data.py
pymoodle_jku/utils/logging.py
pymoodle_jku/utils/login.py
pymoodle_jku/utils/net_usage.py
pymoodle_jku/utils/printing.py
pymoodle_jku-1.2.0.dist-info/LICENSE.txt
pymoodle_jku-1.2.0.dist-info/METADATA
pymoodle_jku-1.2.0.dist-info/WHEEL
pymoodle_jku-1.2.0.dist-info/entry_points.txt
pymoodle_jku-1.2.0.dist-info/top_level.txt
pymoodle_jku-1.2.0.dist-info/RECORD
