Metadata-Version: 2.1
Name: pymoodle-jku
Version: 1.2.0
Summary: A client for the moodle page of JKU Linz.
Home-page: https://github.com/LeLunZ/pymoodle-jku-linz
Download-URL: https://github.com/LeLunZ/pymoodle-jku-linz/archive/pymoodle-jku-1.2.0.tar.gz
Author: LeLunZ
Author-email: l.accounts+pypi@pm.me
License: BSD 3-Clause
Keywords: moodle,jku,linz,jku linz
Classifier: Development Status :: 5 - Production/Stable
Classifier: Intended Audience :: Developers
Classifier: Intended Audience :: End Users/Desktop
Classifier: Topic :: Software Development
Classifier: Topic :: Software Development :: Build Tools
Classifier: Topic :: Utilities
Classifier: Topic :: Education
Classifier: Topic :: Internet :: WWW/HTTP :: Indexing/Search
Classifier: Typing :: Typed
Classifier: License :: OSI Approved :: BSD License
Classifier: Environment :: Console
Classifier: Programming Language :: Python :: 3
Classifier: Programming Language :: Python :: 3.8
Classifier: Programming Language :: Python :: 3.9
Classifier: Natural Language :: English
Requires-Python: >=3.9
License-File: LICENSE.txt
Requires-Dist: argcomplete (==2.0.0)
Requires-Dist: cryptography (==37.0.2)
Requires-Dist: antimarkdown (==1.0.2)
Requires-Dist: keyring (==23.6.0)
Requires-Dist: io-uuid (==0.0.5)
Requires-Dist: lxml (==4.9.1)
Requires-Dist: pick (==1.2.0)
Requires-Dist: readchar (==3.0.5)
Requires-Dist: pytube (==12.1.0)
Requires-Dist: sty (==1.0.4)
Requires-Dist: urllib3 (==1.26.9)
Requires-Dist: requests (==2.28.1)
Requires-Dist: requests-futures (==1.0.0)
Requires-Dist: packaging (==21.3)
Requires-Dist: argparse (~=1.4.0)
Requires-Dist: psutil (==5.9.1)
